vipul/__init__.py
vipul/artificialintel.py
vipul/month.py
vipul/numbers.py
vipul/operators.py
vipul/subjectpercent.py
vipul/surfacearea.py
vipul-0.0.2.dist-info/License.txt
vipul-0.0.2.dist-info/METADATA
vipul-0.0.2.dist-info/WHEEL
vipul-0.0.2.dist-info/top_level.txt
vipul-0.0.2.dist-info/RECORD
