Metadata-Version: 2.1
Name: vipul
Version: 0.0.2
Summary: This Package Is Made By Drake Parker
Home-page: UNKNOWN
Author: Drake Parker
License: UNKNOWN
Platform: UNKNOWN
License-File: License.txt
